{
  "api": {
    "cards": {
      "dependsOn": [],
      "output": {
        "authConfig": {
          "additionalAuthenticationProviders": [],
          "defaultAuthentication": {
            "apiKeyConfig": {
              "apiKeyExpirationDays": 7
            },
            "authenticationType": "API_KEY"
          }
        }
      },
      "providerPlugin": "awscloudformation",
      "service": "AppSync"
    }
  },
  "hosting": {
    "amplifyhosting": {
      "lastPushTimeStamp": "2023-11-27T03:22:32.693Z",
      "service": "amplifyhosting",
      "type": "cicd"
    }
  }
}